odoo/addons/partner_title/README.rst
odoo/addons/partner_title/__init__.py
odoo/addons/partner_title/__manifest__.py
odoo/addons/partner_title/data/res_partner_title.xml
odoo/addons/partner_title/demo/res_partner.xml
odoo/addons/partner_title/i18n/fr.po
odoo/addons/partner_title/i18n/partner_title.pot
odoo/addons/partner_title/models/__init__.py
odoo/addons/partner_title/models/res_partner.py
odoo/addons/partner_title/models/res_partner_title.py
odoo/addons/partner_title/readme/CONFIGURE.md
odoo/addons/partner_title/readme/CONTRIBUTORS.md
odoo/addons/partner_title/readme/DESCRIPTION.md
odoo/addons/partner_title/security/ir.model.access.csv
odoo/addons/partner_title/static/description/icon.png
odoo/addons/partner_title/static/description/index.html
odoo/addons/partner_title/tests/__init__.py
odoo/addons/partner_title/tests/test_partner_title.py
odoo/addons/partner_title/views/res_partner.xml
odoo/addons/partner_title/views/res_partner_title.xml
odoo_addon_partner_title-19.0.1.0.0.2.dist-info/METADATA
odoo_addon_partner_title-19.0.1.0.0.2.dist-info/WHEEL
odoo_addon_partner_title-19.0.1.0.0.2.dist-info/top_level.txt
odoo_addon_partner_title-19.0.1.0.0.2.dist-info/RECORD
